{"name":"设计","slug":"设计","count":3,"postlist":[{"title":"Login Page 设计演示01","uid":"6fcc820b9ac2c2a3332c50f6a1ac1644","slug":"design_LoginPage_2021_11_01","date":"2021-10-31T17:33:52.000Z","updated":"2023-11-26T10:38:32.669Z","comments":true,"path":"api/articles/design_LoginPage_2021_11_01.json","keywords":null,"cover":"https://z3.ax1x.com/2021/11/01/IpzNu9.jpg","text":"分享大家一个好看的 Login Page 代码 演示图 演示代码&lt;!-- Developer: @Arvin Explain: Login Page --...","link":"","photos":[],"count_time":{"symbolsCount":"46k","symbolsTime":"41 mins."},"categories":[{"name":"Web Page","slug":"Web-Page","count":3,"path":"api/categories/Web-Page.json"}],"tags":[{"name":"设计","slug":"设计","count":3,"path":"api/tags/设计.json"}],"author":{"name":"Arvin","slug":"blog-author","avatar":"/imgs/head.jpg","link":"/","description":"","socials":{"github":"","twitter":"","stackoverflow":"","wechat":"","qq":"","weibo":"","zhihu":"","csdn":"","juejin":"","customs":{}}}},{"title":"Error Page 设计演示01","uid":"922522eb16175498ad4c55c094fe3b58","slug":"design_ErrorPage_2021_10_31","date":"2021-10-30T17:23:52.000Z","updated":"2023-11-26T10:38:32.669Z","comments":true,"path":"api/articles/design_ErrorPage_2021_10_31.json","keywords":null,"cover":"https://z3.ax1x.com/2021/10/31/5z70Rx.png","text":"分享大家一个好看的 Error Page 代码 演示图 演示代码&lt;!-- Developer: @Arvin Explain: Error Page --...","link":"","photos":[],"count_time":{"symbolsCount":"5.3k","symbolsTime":"5 mins."},"categories":[{"name":"Web Page","slug":"Web-Page","count":3,"path":"api/categories/Web-Page.json"}],"tags":[{"name":"设计","slug":"设计","count":3,"path":"api/tags/设计.json"}],"author":{"name":"Arvin","slug":"blog-author","avatar":"/imgs/head.jpg","link":"/","description":"","socials":{"github":"","twitter":"","stackoverflow":"","wechat":"","qq":"","weibo":"","zhihu":"","csdn":"","juejin":"","customs":{}}}},{"title":"404 Page 设计演示01","uid":"e110ea6fbbf317e355920dc93f9f4635","slug":"design_404Page_2021_10_31","date":"2021-10-30T17:13:52.000Z","updated":"2023-11-26T10:38:32.669Z","comments":true,"path":"api/articles/design_404Page_2021_10_31.json","keywords":null,"cover":"https://z3.ax1x.com/2021/10/31/5zTL26.png","text":"分享大家一个好看的 404 Page 代码 演示图 代码演示&lt;!-- Developer: @Arvin Explain: 404 Page --&gt;...","link":"","photos":[],"count_time":{"symbolsCount":"6.3k","symbolsTime":"6 mins."},"categories":[{"name":"Web Page","slug":"Web-Page","count":3,"path":"api/categories/Web-Page.json"}],"tags":[{"name":"设计","slug":"设计","count":3,"path":"api/tags/设计.json"}],"author":{"name":"Arvin","slug":"blog-author","avatar":"/imgs/head.jpg","link":"/","description":"","socials":{"github":"","twitter":"","stackoverflow":"","wechat":"","qq":"","weibo":"","zhihu":"","csdn":"","juejin":"","customs":{}}}}]}