{"name":"Script","slug":"Script","count":2,"postlist":[{"title":"TypeScript 程序流程","uid":"024c24535770958fe5fa10d3d115c7c9","slug":"TypeScript_JS_Learning_2021_12_6_01","date":"2021-12-06T07:22:52.000Z","updated":"2023-11-26T10:38:32.669Z","comments":true,"path":"api/articles/TypeScript_JS_Learning_2021_12_6_01.json","keywords":null,"cover":"https://th.bing.com/th/id/R.dc288c8099126dcd9dac931dba803328?rik=UT7Q8NHUjM78nw&riu=http%3a%2f%2fbloghoctap.com%2fwp-content%2fuploads%2f2017%2f01%2ftypescript.jpg&ehk=sAVZdoJHlKzU%2b7PmPVy5RFSx74EWpBmneW7oTdKbFvM%3d&risl=&pid=ImgRaw&r=0","text":"运算符算术运算符 运算符 说明 + 加号 - 减号 * 乘号 &#x2F; 除号 % 取余（取模） ++ | – 自增 | 自减 比较运算符 运算符 说明 &g...","link":"","photos":[],"count_time":{"symbolsCount":"5k","symbolsTime":"5 mins."},"categories":[{"name":"Script","slug":"Script","count":2,"path":"api/categories/Script.json"}],"tags":[{"name":"程序","slug":"程序","count":11,"path":"api/tags/程序.json"}],"author":{"name":"Arvin","slug":"blog-author","avatar":"/imgs/head.jpg","link":"/","description":"","socials":{"github":"","twitter":"","stackoverflow":"","wechat":"","qq":"","weibo":"","zhihu":"","csdn":"","juejin":"","customs":{}}}},{"title":"TypeScript | JavaScript 变量与常量","uid":"c6bdcca557d7825169a4afae27e58649","slug":"TypeScript_JS_Learning_2021_12_5_01","date":"2021-12-05T12:47:52.000Z","updated":"2023-11-26T10:38:32.669Z","comments":true,"path":"api/articles/TypeScript_JS_Learning_2021_12_5_01.json","keywords":null,"cover":"https://th.bing.com/th/id/R.dc288c8099126dcd9dac931dba803328?rik=UT7Q8NHUjM78nw&riu=http%3a%2f%2fbloghoctap.com%2fwp-content%2fuploads%2f2017%2f01%2ftypescript.jpg&ehk=sAVZdoJHlKzU%2b7PmPVy5RFSx74EWpBmneW7oTdKbFvM%3d&risl=&pid=ImgRaw&r=0","text":"语句介绍输出语句 document.write(); 只支持输出为字符串类型 TypeScript document.write(&quot;Hello Wor...","link":"","photos":[],"count_time":{"symbolsCount":"3.7k","symbolsTime":"3 mins."},"categories":[{"name":"Script","slug":"Script","count":2,"path":"api/categories/Script.json"}],"tags":[{"name":"程序","slug":"程序","count":11,"path":"api/tags/程序.json"}],"author":{"name":"Arvin","slug":"blog-author","avatar":"/imgs/head.jpg","link":"/","description":"","socials":{"github":"","twitter":"","stackoverflow":"","wechat":"","qq":"","weibo":"","zhihu":"","csdn":"","juejin":"","customs":{}}}}]}